screenbench/__init__.py
screenbench/basebenchmark.py
screenbench/benchmark_result.py
screenbench/chat_message.py
screenbench/registry.py
screenbench/resize_image.py
screenbench/response_generation.py
screenbench/utils.py
screenbench/agents/__init__.py
screenbench/agents/models.py
screenbench/agents/prompt.py
screenbench/agents/qwentest.py
screenbench/agents/requirements.txt
screenbench/agents/run.py
screenbench/agents/client/android_env_client.py
screenbench/agents/client/desktop_env_client.py
screenbench/agents/client/osworld_vm_downloader.py
screenbench/agents/remote_env/__init__.py
screenbench/agents/remote_env/create_remote_env.py
screenbench/agents/remote_env/provider.py
screenbench/agents/remote_env/docker/provider.py
screenbench/agents/vision_agents/android_agent.py
screenbench/agents/vision_agents/base_vision_agent.py
screenbench/agents/vision_agents/desktop_agent.py
screenbench/agents/vision_agents/e2b_agent.py
screenbench/benchmarks/hubbasebenchmark.py
screenbench/benchmarks/model.py
screenbench/benchmarks/utils.py
screenbench/benchmarks/multistep/__init__.py
screenbench/benchmarks/multistep/config.py
screenbench/benchmarks/multistep/generation.py
screenbench/benchmarks/multistep/android_world/README.md
screenbench/benchmarks/multistep/android_world/__init__.py
screenbench/benchmarks/multistep/android_world/benchmark.py
screenbench/benchmarks/multistep/android_world/config.py
screenbench/benchmarks/multistep/android_world/make_hub_dataset.py
screenbench/benchmarks/multistep/android_world/task_metadata.json
screenbench/benchmarks/multistep/browse_comp/__init__.py
screenbench/benchmarks/multistep/browse_comp/benchmark.py
screenbench/benchmarks/multistep/browse_comp/config.py
screenbench/benchmarks/multistep/browse_comp/prompts.py
screenbench/benchmarks/multistep/browse_comp/tests/test_browse_comp.py
screenbench/benchmarks/multistep/gaia/__init__.py
screenbench/benchmarks/multistep/gaia/benchmark.py
screenbench/benchmarks/multistep/gaia/config.py
screenbench-0.0.1.dist-info/METADATA
screenbench-0.0.1.dist-info/WHEEL
screenbench-0.0.1.dist-info/licenses/LICENSE
screenbench-0.0.1.dist-info/RECORD
